vdropbox/__init__.py
vdropbox/vdropbox.py
vdropbox-1.0.2.dist-info/METADATA
vdropbox-1.0.2.dist-info/WHEEL
vdropbox-1.0.2.dist-info/top_level.txt
vdropbox-1.0.2.dist-info/RECORD
