Metadata-Version: 2.2
Name: vdropbox
Version: 1.0.2
Summary: Utilities to read/write python objects to/from dropbox
Author-email: Arnau Villoro <arnau@villoro.com>
Maintainer-email: Arnau Villoro <arnau@villoro.com>
License: MIT
Classifier: Development Status :: 4 - Beta
Classifier: Intended Audience :: Developers
Classifier: Topic :: Security
Classifier: Topic :: Utilities
Classifier: License :: OSI Approved :: MIT License
Classifier: Programming Language :: Python
Classifier: Programming Language :: Python :: 3
Classifier: Programming Language :: Python :: 3.10
Classifier: Programming Language :: Python :: 3.11
Classifier: Programming Language :: Python :: 3.12
Requires-Python: >=3.10
Requires-Dist: dropbox>=12.0.2
Requires-Dist: loguru>=0.7.3
Requires-Dist: oyaml>=1.0
Requires-Dist: pandas>=2.2.3
